nanoforce/__init__.py
nanoforce/nanoforce.py
nanoforce-0.3.32.dist-info/LICENSE.txt
nanoforce-0.3.32.dist-info/METADATA
nanoforce-0.3.32.dist-info/WHEEL
nanoforce-0.3.32.dist-info/top_level.txt
nanoforce-0.3.32.dist-info/RECORD
