Metadata-Version: 2.1
Name: nanoforce
Version: 0.3.32
Summary: Package to import and analyse AFM force curves produced using Nanoscope 6
Home-page: https://github.com/crj341/nanoforce
Author: Chris Jones
Author-email: crj341@student.bham.ac.uk
License: UNKNOWN
Platform: UNKNOWN
Classifier: Programming Language :: Python :: 3
Classifier: License :: OSI Approved :: MIT License
Classifier: Operating System :: OS Independent
Requires-Python: >=3.6
Requires-Dist: numpy
Requires-Dist: plotly
Requires-Dist: scipy
Requires-Dist: easygui
Requires-Dist: NSFopen
Requires-Dist: sklearn
